[
  { "title": "Getting started", "path": "getting-started.md" },
  { "title": "Development", "path": "development.md" },
  { "title": "API", "children": [
    { "title": "Engine API", "path": "api/engine.md" },
    { "title": "Key types", "path": "api/types.md" },
    { "title": "RFEngine specifics", "path": "api/rfengine.md" }
  ]},
  { "title": "Platform", "path": "platform.md" },
  { "title": "Rendering", "path": "rendering.md" },
  { "title": "Examples & Benchmarks", "path": "examples.md" },
  { "title": "Releases", "path": "releases.md" },
  { "title": "Contributing", "path": "CONTRIBUTING.md" }
]